eclipsegen/__init__.py
eclipsegen/config.py
eclipsegen/generate.py
eclipsegen/preset.py
eclipsegen/tests/__init__.py
eclipsegen/tests/test_eclipsegen.py
eclipsegen-0.5.0.dist-info/METADATA
eclipsegen-0.5.0.dist-info/WHEEL
eclipsegen-0.5.0.dist-info/licenses/LICENSE
eclipsegen-0.5.0.dist-info/licenses/NOTICE
eclipsegen-0.5.0.dist-info/RECORD
