Metadata-Version: 2.1
Name: eclipsegen
Version: 0.5.0
Summary: Generate Eclipse instances in Python
Project-URL: Homepage, https://github.com/Gohla/eclipsegen/
Author-email: Gabriel Konat <gabrielkonat@gmail.com>
License-Expression: Apache-2.0
License-File: LICENSE
License-File: NOTICE
Classifier: License :: OSI Approved :: Apache Software License
Classifier: Operating System :: OS Independent
Classifier: Programming Language :: Python :: 3
Requires-Python: >=3.10
Requires-Dist: requests~=2.7
Provides-Extra: test
Requires-Dist: pytest~=6.0; extra == 'test'
